[{"RouteId": 51, "TripId": 2761, "TimeTableId": 55, "StartTime": "05:00", "EndTime": "06:20"}, {"RouteId": 51, "TripId": 2762, "TimeTableId": 55, "StartTime": "05:15", "EndTime": "06:35"}, {"RouteId": 51, "TripId": 2763, "TimeTableId": 55, "StartTime": "05:30", "EndTime": "06:50"}, {"RouteId": 51, "TripId": 2764, "TimeTableId": 55, "StartTime": "05:42", "EndTime": "07:02"}, {"RouteId": 51, "TripId": 2765, "TimeTableId": 55, "StartTime": "05:54", "EndTime": "07:14"}, {"RouteId": 51, "TripId": 2766, "TimeTableId": 55, "StartTime": "06:06", "EndTime": "07:36"}, {"RouteId": 51, "TripId": 2767, "TimeTableId": 55, "StartTime": "06:18", "EndTime": "07:48"}, {"RouteId": 51, "TripId": 2768, "TimeTableId": 55, "StartTime": "06:30", "EndTime": "08:00"}, {"RouteId": 51, "TripId": 2769, "TimeTableId": 55, "StartTime": "06:42", "EndTime": "08:12"}, {"RouteId": 51, "TripId": 2770, "TimeTableId": 55, "StartTime": "06:54", "EndTime": "08:24"}, {"RouteId": 51, "TripId": 2771, "TimeTableId": 55, "StartTime": "07:06", "EndTime": "08:36"}, {"RouteId": 51, "TripId": 2772, "TimeTableId": 55, "StartTime": "07:18", "EndTime": "08:48"}, {"RouteId": 51, "TripId": 2773, "TimeTableId": 55, "StartTime": "07:30", "EndTime": "09:00"}, {"RouteId": 51, "TripId": 2774, "TimeTableId": 55, "StartTime": "07:45", "EndTime": "09:15"}, {"RouteId": 51, "TripId": 2775, "TimeTableId": 55, "StartTime": "08:00", "EndTime": "09:30"}, {"RouteId": 51, "TripId": 2776, "TimeTableId": 55, "StartTime": "08:15", "EndTime": "09:45"}, {"RouteId": 51, "TripId": 2777, "TimeTableId": 55, "StartTime": "08:30", "EndTime": "10:00"}, {"RouteId": 51, "TripId": 2778, "TimeTableId": 55, "StartTime": "08:45", "EndTime": "10:15"}, {"RouteId": 51, "TripId": 2779, "TimeTableId": 55, "StartTime": "09:00", "EndTime": "10:30"}, {"RouteId": 51, "TripId": 2780, "TimeTableId": 55, "StartTime": "09:15", "EndTime": "10:45"}, {"RouteId": 51, "TripId": 2781, "TimeTableId": 55, "StartTime": "09:30", "EndTime": "11:00"}, {"RouteId": 51, "TripId": 2782, "TimeTableId": 55, "StartTime": "09:45", "EndTime": "11:15"}, {"RouteId": 51, "TripId": 2783, "TimeTableId": 55, "StartTime": "10:00", "EndTime": "11:30"}, {"RouteId": 51, "TripId": 2784, "TimeTableId": 55, "StartTime": "10:12", "EndTime": "11:42"}, {"RouteId": 51, "TripId": 2785, "TimeTableId": 55, "StartTime": "10:24", "EndTime": "11:54"}, {"RouteId": 51, "TripId": 2786, "TimeTableId": 55, "StartTime": "10:36", "EndTime": "12:06"}, {"RouteId": 51, "TripId": 2787, "TimeTableId": 55, "StartTime": "10:48", "EndTime": "12:18"}, {"RouteId": 51, "TripId": 2788, "TimeTableId": 55, "StartTime": "11:00", "EndTime": "12:30"}, {"RouteId": 51, "TripId": 2789, "TimeTableId": 55, "StartTime": "11:12", "EndTime": "12:42"}, {"RouteId": 51, "TripId": 2790, "TimeTableId": 55, "StartTime": "11:24", "EndTime": "12:54"}, {"RouteId": 51, "TripId": 2791, "TimeTableId": 55, "StartTime": "11:39", "EndTime": "13:09"}, {"RouteId": 51, "TripId": 2792, "TimeTableId": 55, "StartTime": "11:54", "EndTime": "13:24"}, {"RouteId": 51, "TripId": 2793, "TimeTableId": 55, "StartTime": "12:09", "EndTime": "13:39"}, {"RouteId": 51, "TripId": 2794, "TimeTableId": 55, "StartTime": "12:24", "EndTime": "13:54"}, {"RouteId": 51, "TripId": 2795, "TimeTableId": 55, "StartTime": "12:42", "EndTime": "14:12"}, {"RouteId": 51, "TripId": 2796, "TimeTableId": 55, "StartTime": "13:00", "EndTime": "14:30"}, {"RouteId": 51, "TripId": 2797, "TimeTableId": 55, "StartTime": "13:20", "EndTime": "14:50"}, {"RouteId": 51, "TripId": 2798, "TimeTableId": 55, "StartTime": "13:40", "EndTime": "15:10"}, {"RouteId": 51, "TripId": 2799, "TimeTableId": 55, "StartTime": "14:00", "EndTime": "15:30"}, {"RouteId": 51, "TripId": 2800, "TimeTableId": 55, "StartTime": "14:20", "EndTime": "15:50"}, {"RouteId": 51, "TripId": 2801, "TimeTableId": 55, "StartTime": "14:38", "EndTime": "16:08"}, {"RouteId": 51, "TripId": 2802, "TimeTableId": 55, "StartTime": "14:56", "EndTime": "16:26"}, {"RouteId": 51, "TripId": 2803, "TimeTableId": 55, "StartTime": "15:14", "EndTime": "16:44"}, {"RouteId": 51, "TripId": 2804, "TimeTableId": 55, "StartTime": "15:29", "EndTime": "16:59"}, {"RouteId": 51, "TripId": 2805, "TimeTableId": 55, "StartTime": "15:41", "EndTime": "17:11"}, {"RouteId": 51, "TripId": 2806, "TimeTableId": 55, "StartTime": "15:53", "EndTime": "17:23"}, {"RouteId": 51, "TripId": 2807, "TimeTableId": 55, "StartTime": "16:05", "EndTime": "17:35"}, {"RouteId": 51, "TripId": 2808, "TimeTableId": 55, "StartTime": "16:17", "EndTime": "17:47"}, {"RouteId": 51, "TripId": 2809, "TimeTableId": 55, "StartTime": "16:29", "EndTime": "17:59"}, {"RouteId": 51, "TripId": 2810, "TimeTableId": 55, "StartTime": "16:41", "EndTime": "18:11"}, {"RouteId": 51, "TripId": 2811, "TimeTableId": 55, "StartTime": "16:53", "EndTime": "18:23"}, {"RouteId": 51, "TripId": 2812, "TimeTableId": 55, "StartTime": "17:05", "EndTime": "18:35"}, {"RouteId": 51, "TripId": 2813, "TimeTableId": 55, "StartTime": "17:17", "EndTime": "18:47"}, {"RouteId": 51, "TripId": 2814, "TimeTableId": 55, "StartTime": "17:29", "EndTime": "18:59"}, {"RouteId": 51, "TripId": 2815, "TimeTableId": 55, "StartTime": "17:41", "EndTime": "19:11"}, {"RouteId": 51, "TripId": 2816, "TimeTableId": 55, "StartTime": "17:53", "EndTime": "19:23"}, {"RouteId": 51, "TripId": 2817, "TimeTableId": 55, "StartTime": "18:08", "EndTime": "19:38"}, {"RouteId": 51, "TripId": 2818, "TimeTableId": 55, "StartTime": "18:23", "EndTime": "19:53"}, {"RouteId": 51, "TripId": 2819, "TimeTableId": 55, "StartTime": "18:41", "EndTime": "20:11"}, {"RouteId": 51, "TripId": 2820, "TimeTableId": 55, "StartTime": "19:00", "EndTime": "20:30"}]